ljpypi_test/__init__.py
ljpypi_test/sampleCode.py
ljpypi_test-0.2.0.dist-info/LICENSE
ljpypi_test-0.2.0.dist-info/METADATA
ljpypi_test-0.2.0.dist-info/WHEEL
ljpypi_test-0.2.0.dist-info/top_level.txt
ljpypi_test-0.2.0.dist-info/RECORD
